sample_calculator/__init__.py
sample_calculator-0.1.dist-info/LICENSE.txt
sample_calculator-0.1.dist-info/METADATA
sample_calculator-0.1.dist-info/WHEEL
sample_calculator-0.1.dist-info/top_level.txt
sample_calculator-0.1.dist-info/RECORD
