Metadata-Version: 2.1
Name: sample-calculator
Version: 0.1
Summary: Basic Calculator
Author: Tomra
Author-email: nimritee.sirsalewala@tomra.com
Classifier: Programming Language :: Python :: 3
Classifier: License :: OSI Approved :: MIT License
Classifier: Operating System :: OS Independent
License-File: LICENSE.txt
